[
  {
    "id": "Sngal-Egypte",
    "league": "CAN",
    "team1": {
      "name": "Sénégal",
      "logo": ""
    },
    "team2": {
      "name": "Egypte",
      "logo": ""
    },
    "kickoff_date": "2026-01-15",
    "kickoff_time": "00:00",
    "match_date": "2026-01-15",
    "match_time": "00:00",
    "duration": "3.5",
    "servers": [
      {
        "url": "https://multi.govoet.my.id/?envivo=1",
        "label": "CH-FR"
      },
      {
        "url": "https://multi.govoet.my.id/?envivo=61",
        "label": "CH-ES"
      },
      {
        "url": "https://multi.govoet.my.id/?envivo=82",
        "label": "CH-ES"
      },
      {
        "url": "https://multi.govoet.my.id/?envivo=69",
        "label": "CH-ES"
      },
      {
        "url": "https://multi.govoet.my.id/?envivo=125",
        "label": "CH-DE"
      }
    ]
  },
  {
    "id": "Wolfsburg-StPauli",
    "league": "Bundesliga",
    "team1": {
      "name": "Wolfsburg",
      "logo": ""
    },
    "team2": {
      "name": "St. Pauli",
      "logo": ""
    },
    "kickoff_date": "2026-01-15",
    "kickoff_time": "00:30",
    "match_date": "2026-01-15",
    "match_time": "00:30",
    "duration": "3.5",
    "servers": [
      {
        "url": "https://multi.govoet.my.id/?envivo=6",
        "label": "CH-FR"
      },
      {
        "url": "https://multi.govoet.my.id/?envivo=111",
        "label": "CH-DE"
      },
      {
        "url": "https://multi.govoet.my.id/?envivo=116",
        "label": "CH-ES"
      }
    ]
  },
  {
    "id": "BeyogluYeniCarsi-Fenerbahce",
    "league": "Coupe De Turquie",
    "team1": {
      "name": "Beyoglu Yeni Carsi",
      "logo": ""
    },
    "team2": {
      "name": "Fenerbahce",
      "logo": ""
    },
    "kickoff_date": "2026-01-15",
    "kickoff_time": "00:30",
    "match_date": "2026-01-15",
    "match_time": "00:30",
    "duration": "3.5",
    "servers": [
      {
        "url": "https://multi.govoet.my.id/?envivo=151",
        "label": "CH-TR"
      }
    ]
  },
  {
    "id": "AlAhliSC-AlTaawon",
    "league": "Saudi Pro League",
    "team1": {
      "name": "Al Ahli SC",
      "logo": ""
    },
    "team2": {
      "name": "Al-Taawon",
      "logo": ""
    },
    "kickoff_date": "2026-01-15",
    "kickoff_time": "00:30",
    "match_date": "2026-01-15",
    "match_time": "00:30",
    "duration": "3.5",
    "servers": [
      {
        "url": "https://multi.govoet.my.id/?envivo=50",
        "label": "CH-ES"
      }
    ]
  },
  {
    "id": "Naples-Parme",
    "league": "Serie A",
    "team1": {
      "name": "Naples",
      "logo": ""
    },
    "team2": {
      "name": "Parme",
      "logo": ""
    },
    "kickoff_date": "2026-01-15",
    "kickoff_time": "00:30",
    "match_date": "2026-01-15",
    "match_time": "00:30",
    "duration": "3.5",
    "servers": [
      {
        "url": "https://multi.govoet.my.id/?envivo=137",
        "label": "CH-IT"
      },
      {
        "url": "https://multi.govoet.my.id/?envivo=124",
        "label": "CH-DE"
      },
      {
        "url": "https://multi.govoet.my.id/?envivo=87",
        "label": "CH-ES"
      },
      {
        "url": "https://multi.govoet.my.id/?envivo=98",
        "label": "CH-ES"
      },
      {
        "url": "https://multi.govoet.my.id/?envivo=70",
        "label": "CH-ES"
      }
    ]
  },
  {
    "id": "DenBosch-PSV",
    "league": "Knvb Beker",
    "team1": {
      "name": "Den Bosch",
      "logo": ""
    },
    "team2": {
      "name": "PSV",
      "logo": ""
    },
    "kickoff_date": "2026-01-15",
    "kickoff_time": "00:45",
    "match_date": "2026-01-15",
    "match_time": "00:45",
    "duration": "3.5",
    "servers": [
      {
        "url": "https://multi.govoet.my.id/?envivo=142",
        "label": "CH-NL"
      },
      {
        "url": "https://multi.govoet.my.id/?envivo=96",
        "label": "CH-ES"
      }
    ]
  },
  {
    "id": "MarseilleF-SainttienneF",
    "league": "D1 Féminin",
    "team1": {
      "name": "Marseille F",
      "logo": ""
    },
    "team2": {
      "name": "Saint-Étienne F",
      "logo": ""
    },
    "kickoff_date": "2026-01-15",
    "kickoff_time": "01:00",
    "match_date": "2026-01-15",
    "match_time": "01:00",
    "duration": "3.5",
    "servers": [
      {
        "url": "https://multi.govoet.my.id/?envivo=12",
        "label": "CH-FR"
      }
    ]
  },
  {
    "id": "Panathinaikos-Aris",
    "league": "Coupe De Grèce",
    "team1": {
      "name": "Panathinaikos",
      "logo": ""
    },
    "team2": {
      "name": "Aris",
      "logo": ""
    },
    "kickoff_date": "2026-01-15",
    "kickoff_time": "01:30",
    "match_date": "2026-01-15",
    "match_time": "01:30",
    "duration": "3.5",
    "servers": [
      {
        "url": "https://multi.govoet.my.id/?envivo=148",
        "label": "CH-GR"
      }
    ]
  },
  {
    "id": "Partizan-Olympiakos",
    "league": "EuroLeague",
    "team1": {
      "name": "Partizan",
      "logo": ""
    },
    "team2": {
      "name": "Olympiakos",
      "logo": ""
    },
    "kickoff_date": "2026-01-15",
    "kickoff_time": "01:30",
    "match_date": "2026-01-15",
    "match_time": "01:30",
    "duration": "3.5",
    "servers": [
      {
        "url": "https://multi.govoet.my.id/?envivo=62",
        "label": "CH-ES"
      },
      {
        "url": "https://multi.govoet.my.id/?envivo=95",
        "label": "CH-ES"
      }
    ]
  },
  {
    "id": "Fafe-Braga",
    "league": "Coupe Du Portugal",
    "team1": {
      "name": "Fafe",
      "logo": ""
    },
    "team2": {
      "name": "Braga",
      "logo": ""
    },
    "kickoff_date": "2026-01-15",
    "kickoff_time": "01:45",
    "match_date": "2026-01-15",
    "match_time": "01:45",
    "duration": "3.5",
    "servers": [
      {
        "url": "https://multi.govoet.my.id/?envivo=145",
        "label": "CH-PT"
      }
    ]
  },
  {
    "id": "AlmereCity-Telstar",
    "league": "Knvb Beker",
    "team1": {
      "name": "Almere City",
      "logo": ""
    },
    "team2": {
      "name": "Telstar",
      "logo": ""
    },
    "kickoff_date": "2026-01-15",
    "kickoff_time": "02:00",
    "match_date": "2026-01-15",
    "match_time": "02:00",
    "duration": "3.5",
    "servers": [
      {
        "url": "https://multi.govoet.my.id/?envivo=147",
        "label": "CH-NL"
      }
    ]
  },
  {
    "id": "GAEagles-Heracles",
    "league": "Knvb Beker",
    "team1": {
      "name": "G.A. Eagles",
      "logo": ""
    },
    "team2": {
      "name": "Heracles",
      "logo": ""
    },
    "kickoff_date": "2026-01-15",
    "kickoff_time": "02:00",
    "match_date": "2026-01-15",
    "match_time": "02:00",
    "duration": "3.5",
    "servers": [
      {
        "url": "https://multi.govoet.my.id/?envivo=143",
        "label": "CH-NL"
      }
    ]
  },
  {
    "id": "bundesligakonferenz",
    "league": "Bundesliga",
    "team1": {
      "name": "bundesliga konferenz -",
      "logo": ""
    },
    "team2": {
      "name": "",
      "logo": ""
    },
    "kickoff_date": "2026-01-15",
    "kickoff_time": "02:30",
    "match_date": "2026-01-15",
    "match_time": "02:30",
    "duration": "3.5",
    "servers": [
      {
        "url": "https://multi.govoet.my.id/?envivo=123",
        "label": "CH-DE"
      }
    ]
  },
  {
    "id": "FCCologne-BayernMunich",
    "league": "Bundesliga",
    "team1": {
      "name": "FC Cologne",
      "logo": ""
    },
    "team2": {
      "name": "Bayern Munich",
      "logo": ""
    },
    "kickoff_date": "2026-01-15",
    "kickoff_time": "02:30",
    "match_date": "2026-01-15",
    "match_time": "02:30",
    "duration": "3.5",
    "servers": [
      {
        "url": "https://multi.govoet.my.id/?envivo=3",
        "label": "CH-FR"
      },
      {
        "url": "https://multi.govoet.my.id/?envivo=112",
        "label": "CH-DE"
      },
      {
        "url": "https://multi.govoet.my.id/?envivo=117",
        "label": "CH-ES"
      }
    ]
  },
  {
    "id": "Hoffenheim-BMonchengladbach",
    "league": "Bundesliga",
    "team1": {
      "name": "Hoffenheim",
      "logo": ""
    },
    "team2": {
      "name": "B. Monchengladbach",
      "logo": ""
    },
    "kickoff_date": "2026-01-15",
    "kickoff_time": "02:30",
    "match_date": "2026-01-15",
    "match_time": "02:30",
    "duration": "3.5",
    "servers": [
      {
        "url": "https://multi.govoet.my.id/?envivo=8",
        "label": "CH-FR"
      },
      {
        "url": "https://multi.govoet.my.id/?envivo=114",
        "label": "CH-DE"
      },
      {
        "url": "https://multi.govoet.my.id/?envivo=88",
        "label": "CH-ES"
      },
      {
        "url": "https://multi.govoet.my.id/?envivo=118",
        "label": "CH-ES"
      }
    ]
  },
  {
    "id": "RBLeipzig-Fribourg",
    "league": "Bundesliga",
    "team1": {
      "name": "RB Leipzig",
      "logo": ""
    },
    "team2": {
      "name": "Fribourg",
      "logo": ""
    },
    "kickoff_date": "2026-01-15",
    "kickoff_time": "02:30",
    "match_date": "2026-01-15",
    "match_time": "02:30",
    "duration": "3.5",
    "servers": [
      {
        "url": "https://multi.govoet.my.id/?envivo=7",
        "label": "CH-FR"
      },
      {
        "url": "https://multi.govoet.my.id/?envivo=113",
        "label": "CH-DE"
      },
      {
        "url": "https://multi.govoet.my.id/?envivo=119",
        "label": "CH-ES"
      }
    ]
  },
  {
    "id": "Dender-RoyaleUnionSG",
    "league": "Coupe De Belgique",
    "team1": {
      "name": "Dender",
      "logo": ""
    },
    "team2": {
      "name": "Royale Union SG",
      "logo": ""
    },
    "kickoff_date": "2026-01-15",
    "kickoff_time": "02:30",
    "match_date": "2026-01-15",
    "match_time": "02:30",
    "duration": "3.5",
    "servers": [
      {
        "url": "https://multi.govoet.my.id/?envivo=153",
        "label": "CH-FR"
      }
    ]
  },
  {
    "id": "Falkirk-Celtic",
    "league": "Premiership",
    "team1": {
      "name": "Falkirk",
      "logo": ""
    },
    "team2": {
      "name": "Celtic",
      "logo": ""
    },
    "kickoff_date": "2026-01-15",
    "kickoff_time": "02:45",
    "match_date": "2026-01-15",
    "match_time": "02:45",
    "duration": "3.5",
    "servers": [
      {
        "url": "https://multi.govoet.my.id/?envivo=135",
        "label": "CH-US"
      }
    ]
  },
  {
    "id": "Inter-Lecce",
    "league": "Serie A",
    "team1": {
      "name": "Inter",
      "logo": ""
    },
    "team2": {
      "name": "Lecce",
      "logo": ""
    },
    "kickoff_date": "2026-01-15",
    "kickoff_time": "02:45",
    "match_date": "2026-01-15",
    "match_time": "02:45",
    "duration": "3.5",
    "servers": [
      {
        "url": "https://multi.govoet.my.id/?envivo=137",
        "label": "CH-IT"
      },
      {
        "url": "https://multi.govoet.my.id/?envivo=124",
        "label": "CH-DE"
      },
      {
        "url": "https://multi.govoet.my.id/?envivo=159",
        "label": "CH-ES"
      }
    ]
  },
  {
    "id": "Nigria-Maroc",
    "league": "CAN",
    "team1": {
      "name": "Nigéria",
      "logo": ""
    },
    "team2": {
      "name": "Maroc",
      "logo": ""
    },
    "kickoff_date": "2026-01-15",
    "kickoff_time": "03:00",
    "match_date": "2026-01-15",
    "match_time": "03:00",
    "duration": "3.5",
    "servers": [
      {
        "url": "https://multi.govoet.my.id/?envivo=1",
        "label": "CH-FR"
      },
      {
        "url": "https://multi.govoet.my.id/?envivo=61",
        "label": "CH-ES"
      },
      {
        "url": "https://multi.govoet.my.id/?envivo=81",
        "label": "CH-ES"
      },
      {
        "url": "https://multi.govoet.my.id/?envivo=69",
        "label": "CH-ES"
      },
      {
        "url": "https://multi.govoet.my.id/?envivo=125",
        "label": "CH-DE"
      }
    ]
  },
  {
    "id": "Alaves-Vallecano",
    "league": "Coupe Du Roi",
    "team1": {
      "name": "Alaves",
      "logo": ""
    },
    "team2": {
      "name": "Vallecano",
      "logo": ""
    },
    "kickoff_date": "2026-01-15",
    "kickoff_time": "03:00",
    "match_date": "2026-01-15",
    "match_time": "03:00",
    "duration": "3.5",
    "servers": [
      {
        "url": "https://multi.govoet.my.id/?envivo=162",
        "label": "CH-ES"
      }
    ]
  },
  {
    "id": "Albacete-RealMadrid",
    "league": "Coupe Du Roi",
    "team1": {
      "name": "Albacete",
      "logo": ""
    },
    "team2": {
      "name": "Real Madrid",
      "logo": ""
    },
    "kickoff_date": "2026-01-15",
    "kickoff_time": "03:00",
    "match_date": "2026-01-15",
    "match_time": "03:00",
    "duration": "3.5",
    "servers": [
      {
        "url": "https://multi.govoet.my.id/?envivo=60",
        "label": "CH-ES"
      },
      {
        "url": "https://multi.govoet.my.id/?envivo=82",
        "label": "CH-ES"
      }
    ]
  },
  {
    "id": "Betis-Elche",
    "league": "Coupe Du Roi",
    "team1": {
      "name": "Betis",
      "logo": ""
    },
    "team2": {
      "name": "Elche",
      "logo": ""
    },
    "kickoff_date": "2026-01-15",
    "kickoff_time": "03:00",
    "match_date": "2026-01-15",
    "match_time": "03:00",
    "duration": "3.5",
    "servers": [
      {
        "url": "https://multi.govoet.my.id/?envivo=49",
        "label": "CH-ES"
      }
    ]
  },
  {
    "id": "ParisFCF-NantesF",
    "league": "D1 Féminin",
    "team1": {
      "name": "Paris FC F",
      "logo": ""
    },
    "team2": {
      "name": "Nantes F",
      "logo": ""
    },
    "kickoff_date": "2026-01-15",
    "kickoff_time": "03:00",
    "match_date": "2026-01-15",
    "match_time": "03:00",
    "duration": "3.5",
    "servers": [
      {
        "url": "https://multi.govoet.my.id/?envivo=12",
        "label": "CH-FR"
      }
    ]
  },
  {
    "id": "Chelsea-Arsenal",
    "league": "Efl Cup",
    "team1": {
      "name": "Chelsea",
      "logo": ""
    },
    "team2": {
      "name": "Arsenal",
      "logo": ""
    },
    "kickoff_date": "2026-01-15",
    "kickoff_time": "03:00",
    "match_date": "2026-01-15",
    "match_time": "03:00",
    "duration": "3.5",
    "servers": [
      {
        "url": "https://multi.govoet.my.id/?envivo=2",
        "label": "CH-FR"
      },
      {
        "url": "https://multi.govoet.my.id/?envivo=127",
        "label": "CH-GB"
      },
      {
        "url": "https://multi.govoet.my.id/?envivo=120",
        "label": "CH-DE"
      },
      {
        "url": "https://multi.govoet.my.id/?envivo=87",
        "label": "CH-ES"
      },
      {
        "url": "https://multi.govoet.my.id/?envivo=98",
        "label": "CH-ES"
      }
    ]
  },
  {
    "id": "Alkmaar-Ajax",
    "league": "Knvb Beker",
    "team1": {
      "name": "Alkmaar",
      "logo": ""
    },
    "team2": {
      "name": "Ajax",
      "logo": ""
    },
    "kickoff_date": "2026-01-15",
    "kickoff_time": "03:00",
    "match_date": "2026-01-15",
    "match_time": "03:00",
    "duration": "3.5",
    "servers": [
      {
        "url": "https://multi.govoet.my.id/?envivo=141",
        "label": "CH-NL"
      },
      {
        "url": "https://multi.govoet.my.id/?envivo=96",
        "label": "CH-ES"
      }
    ]
  },
  {
    "id": "FCPorto-Benfica",
    "league": "Coupe Du Portugal",
    "team1": {
      "name": "FC Porto",
      "logo": ""
    },
    "team2": {
      "name": "Benfica",
      "logo": ""
    },
    "kickoff_date": "2026-01-15",
    "kickoff_time": "03:45",
    "match_date": "2026-01-15",
    "match_time": "03:45",
    "duration": "3.5",
    "servers": [
      {
        "url": "https://multi.govoet.my.id/?envivo=144",
        "label": "CH-PT"
      }
    ]
  },
  {
    "id": "CruzAzul-Atlas",
    "league": "Liga Mx",
    "team1": {
      "name": "Cruz Azul",
      "logo": ""
    },
    "team2": {
      "name": "Atlas",
      "logo": ""
    },
    "kickoff_date": "2026-01-15",
    "kickoff_time": "06:00",
    "match_date": "2026-01-15",
    "match_time": "06:00",
    "duration": "3.5",
    "servers": [
      {
        "url": "https://multi.govoet.my.id/?envivo=106",
        "label": "CH-ES"
      },
      {
        "url": "https://multi.govoet.my.id/?envivo=107",
        "label": "CH-ES"
      }
    ]
  },
  {
    "id": "IndianaPacers-TorontoRaptors",
    "league": "NBA",
    "team1": {
      "name": "Indiana Pacers",
      "logo": ""
    },
    "team2": {
      "name": "Toronto Raptors",
      "logo": ""
    },
    "kickoff_date": "2026-01-15",
    "kickoff_time": "07:00",
    "match_date": "2026-01-15",
    "match_time": "07:00",
    "duration": "3.5",
    "servers": [
      {
        "url": "https://multi.govoet.my.id/?envivo=180",
        "label": "CH-US"
      }
    ]
  },
  {
    "id": "Philadelphia76ers-ClevelandCavaliers",
    "league": "NBA",
    "team1": {
      "name": "Philadelphia 76ers",
      "logo": ""
    },
    "team2": {
      "name": "Cleveland Cavaliers",
      "logo": ""
    },
    "kickoff_date": "2026-01-15",
    "kickoff_time": "07:00",
    "match_date": "2026-01-15",
    "match_time": "07:00",
    "duration": "3.5",
    "servers": [
      {
        "url": "https://multi.govoet.my.id/?envivo=1",
        "label": "CH-FR"
      },
      {
        "url": "https://multi.govoet.my.id/?envivo=181",
        "label": "CH-US"
      },
      {
        "url": "https://multi.govoet.my.id/?envivo=155",
        "label": "CH-ES"
      },
      {
        "url": "https://multi.govoet.my.id/?envivo=88",
        "label": "CH-ES"
      },
      {
        "url": "https://multi.govoet.my.id/?envivo=97",
        "label": "CH-ES"
      }
    ]
  },
  {
    "id": "NewJerseyDevils-SeattleKraken",
    "league": "NHL",
    "team1": {
      "name": "New Jersey Devils",
      "logo": ""
    },
    "team2": {
      "name": "Seattle Kraken",
      "logo": ""
    },
    "kickoff_date": "2026-01-15",
    "kickoff_time": "07:00",
    "match_date": "2026-01-15",
    "match_time": "07:00",
    "duration": "3.5",
    "servers": [
      {
        "url": "https://multi.govoet.my.id/?envivo=187",
        "label": "CH-US"
      }
    ]
  },
  {
    "id": "BuffaloSabres-PhiladelphiaFlyers",
    "league": "NHL",
    "team1": {
      "name": "Buffalo Sabres",
      "logo": ""
    },
    "team2": {
      "name": "Philadelphia Flyers",
      "logo": ""
    },
    "kickoff_date": "2026-01-15",
    "kickoff_time": "07:30",
    "match_date": "2026-01-15",
    "match_time": "07:30",
    "duration": "3.5",
    "servers": [
      {
        "url": "https://multi.govoet.my.id/?envivo=188",
        "label": "CH-US"
      }
    ]
  },
  {
    "id": "NewYorkRangers-OttawaSenators",
    "league": "NHL",
    "team1": {
      "name": "New York Rangers",
      "logo": ""
    },
    "team2": {
      "name": "Ottawa Senators",
      "logo": ""
    },
    "kickoff_date": "2026-01-15",
    "kickoff_time": "07:30",
    "match_date": "2026-01-15",
    "match_time": "07:30",
    "duration": "3.5",
    "servers": [
      {
        "url": "https://multi.govoet.my.id/?envivo=189",
        "label": "CH-US"
      }
    ]
  },
  {
    "id": "Queretaro-Tijuana",
    "league": "Liga Mx",
    "team1": {
      "name": "Queretaro",
      "logo": ""
    },
    "team2": {
      "name": "Tijuana",
      "logo": ""
    },
    "kickoff_date": "2026-01-15",
    "kickoff_time": "08:00",
    "match_date": "2026-01-15",
    "match_time": "08:00",
    "duration": "3.5",
    "servers": [
      {
        "url": "https://multi.govoet.my.id/?envivo=158",
        "label": "CH-ES"
      }
    ]
  },
  {
    "id": "ChicagoBulls-UtahJazz",
    "league": "NBA",
    "team1": {
      "name": "Chicago Bulls",
      "logo": ""
    },
    "team2": {
      "name": "Utah Jazz",
      "logo": ""
    },
    "kickoff_date": "2026-01-15",
    "kickoff_time": "08:00",
    "match_date": "2026-01-15",
    "match_time": "08:00",
    "duration": "3.5",
    "servers": [
      {
        "url": "https://multi.govoet.my.id/?envivo=182",
        "label": "CH-US"
      }
    ]
  },
  {
    "id": "NewOrleansPelicans-BrooklynNets",
    "league": "NBA",
    "team1": {
      "name": "New Orleans Pelicans",
      "logo": ""
    },
    "team2": {
      "name": "Brooklyn Nets",
      "logo": ""
    },
    "kickoff_date": "2026-01-15",
    "kickoff_time": "08:00",
    "match_date": "2026-01-15",
    "match_time": "08:00",
    "duration": "3.5",
    "servers": [
      {
        "url": "https://multi.govoet.my.id/?envivo=183",
        "label": "CH-US"
      }
    ]
  },
  {
    "id": "ClubAmerica-AtlSanLuis",
    "league": "Liga Mx",
    "team1": {
      "name": "Club America",
      "logo": ""
    },
    "team2": {
      "name": "Atl. San Luis",
      "logo": ""
    },
    "kickoff_date": "2026-01-15",
    "kickoff_time": "08:05",
    "match_date": "2026-01-15",
    "match_time": "08:05",
    "duration": "3.5",
    "servers": [
      {
        "url": "https://multi.govoet.my.id/?envivo=106",
        "label": "CH-ES"
      },
      {
        "url": "https://multi.govoet.my.id/?envivo=107",
        "label": "CH-ES"
      },
      {
        "url": "https://multi.govoet.my.id/?envivo=68",
        "label": "CH-ES"
      }
    ]
  },
  {
    "id": "DallasMavericks-DenverNuggets",
    "league": "NBA",
    "team1": {
      "name": "Dallas Mavericks",
      "logo": ""
    },
    "team2": {
      "name": "Denver Nuggets",
      "logo": ""
    },
    "kickoff_date": "2026-01-15",
    "kickoff_time": "09:30",
    "match_date": "2026-01-15",
    "match_time": "09:30",
    "duration": "3.5",
    "servers": [
      {
        "url": "https://multi.govoet.my.id/?envivo=1",
        "label": "CH-FR"
      },
      {
        "url": "https://multi.govoet.my.id/?envivo=184",
        "label": "CH-US"
      },
      {
        "url": "https://multi.govoet.my.id/?envivo=156",
        "label": "CH-ES"
      },
      {
        "url": "https://multi.govoet.my.id/?envivo=88",
        "label": "CH-ES"
      },
      {
        "url": "https://multi.govoet.my.id/?envivo=97",
        "label": "CH-ES"
      }
    ]
  },
  {
    "id": "SacramentoKings-NewYorkKnicks",
    "league": "NBA",
    "team1": {
      "name": "Sacramento Kings",
      "logo": ""
    },
    "team2": {
      "name": "New York Knicks",
      "logo": ""
    },
    "kickoff_date": "2026-01-15",
    "kickoff_time": "10:00",
    "match_date": "2026-01-15",
    "match_time": "10:00",
    "duration": "3.5",
    "servers": [
      {
        "url": "https://multi.govoet.my.id/?envivo=185",
        "label": "CH-US"
      }
    ]
  },
  {
    "id": "LosAngelesKings-VegasGoldenKnights",
    "league": "NHL",
    "team1": {
      "name": "Los Angeles Kings",
      "logo": ""
    },
    "team2": {
      "name": "Vegas Golden Knights",
      "logo": ""
    },
    "kickoff_date": "2026-01-15",
    "kickoff_time": "10:00",
    "match_date": "2026-01-15",
    "match_time": "10:00",
    "duration": "3.5",
    "servers": [
      {
        "url": "https://multi.govoet.my.id/?envivo=190",
        "label": "CH-US"
      }
    ]
  },
  {
    "id": "Tigres-UNAM",
    "league": "Liga Mx",
    "team1": {
      "name": "Tigres",
      "logo": ""
    },
    "team2": {
      "name": "U.N.A.M.",
      "logo": ""
    },
    "kickoff_date": "2026-01-15",
    "kickoff_time": "10:06",
    "match_date": "2026-01-15",
    "match_time": "10:06",
    "duration": "3.5",
    "servers": [
      {
        "url": "https://multi.govoet.my.id/?envivo=72",
        "label": "CH-ES"
      },
      {
        "url": "https://multi.govoet.my.id/?envivo=108",
        "label": "CH-ES"
      },
      {
        "url": "https://multi.govoet.my.id/?envivo=70",
        "label": "CH-ES"
      }
    ]
  },
  {
    "id": "Toluca-SantosLaguna",
    "league": "Liga Mx",
    "team1": {
      "name": "Toluca",
      "logo": ""
    },
    "team2": {
      "name": "Santos Laguna",
      "logo": ""
    },
    "kickoff_date": "2026-01-15",
    "kickoff_time": "10:10",
    "match_date": "2026-01-15",
    "match_time": "10:10",
    "duration": "3.5",
    "servers": [
      {
        "url": "https://multi.govoet.my.id/?envivo=106",
        "label": "CH-ES"
      },
      {
        "url": "https://multi.govoet.my.id/?envivo=107",
        "label": "CH-ES"
      },
      {
        "url": "https://multi.govoet.my.id/?envivo=68",
        "label": "CH-ES"
      }
    ]
  },
  {
    "id": "LosAngelesClippers-WashingtonWizards",
    "league": "NBA",
    "team1": {
      "name": "Los Angeles Clippers",
      "logo": ""
    },
    "team2": {
      "name": "Washington Wizards",
      "logo": ""
    },
    "kickoff_date": "2026-01-15",
    "kickoff_time": "10:30",
    "match_date": "2026-01-15",
    "match_time": "10:30",
    "duration": "3.5",
    "servers": [
      {
        "url": "https://multi.govoet.my.id/?envivo=186",
        "label": "CH-US"
      }
    ]
  }
]