[
    {
        "id": "G.A.Eagles-Heerenveen",
        "sport": "Football",
        "league": "NED Eredivisie",
        "team1": {
            "name": "G.A. Eagles",
            "logo": "https://ikotv.com/storage/logos/rgj4XeZA-CYLEXeh5 (3).png"
        },
        "team2": {
            "name": "Heerenveen",
            "logo": "https://ikotv.com/storage/logos/jN0XaHYg-4vob7cTR (3).png"
        },
        "kickoff_date": "2026-02-12",
        "kickoff_time": "00:45",
        "match_date": "2026-02-12",
        "match_time": "00:45",
        "duration": "3.5",
        "servers": [
            {
                "url": "https://multi.govoet.cc/?hls=aHR0cHM6Ly90ZXN0LmJ0eXNvMTYuY29tL2xpdmUvc2QtNk11VDdocENaNGpjd1d1TkozLm0zdTg/dHhTZWNyZXQ9ZDRkN2M0ZmE1MzJhNjgzNTFhYTViMDg4YzcxZjViZTQmdHhUaW1lPTY5OEUxMkY3",
                "label": "CH-NA"
            },
            {
                "url": "https://multi.govoet.cc/?hls=aHR0cHM6Ly9saXZlMS56dXFpdXp1cWl1enVxaXV6dXFpdS5jb20vc3BvcnQvMjAyXzQ0MTgwODZfMS5tM3U4",
                "label": "CH-NA"
            }
        ]
    },
    {
        "id": "Leuven(W)-Arsenal(W)",
        "sport": "Football",
        "league": "Champions League Women",
        "team1": {
            "name": "Leuven (W)",
            "logo": "https://ikotv.com/storage/logos/WKHuTSYA-KO6bNwa1 (1).png"
        },
        "team2": {
            "name": "Arsenal (W)",
            "logo": "https://ikotv.com/storage/logos/WbvWGBEG-QmAvFdvS (2).png"
        },
        "kickoff_date": "2026-02-12",
        "kickoff_time": "00:45",
        "match_date": "2026-02-12",
        "match_time": "00:45",
        "duration": "3.5",
        "servers": [
            {
                "url": "https://multi.govoet.cc/?hls=aHR0cHM6Ly90ZXN0LmJ0eXNvMTYuY29tL2xpdmUvc2QtNk12WjZIZDNGWHlOdWp2RjNtLm0zdTg/dHhTZWNyZXQ9YmY3ZjIxZTE3NjFiZjIxYzA2OTYyZTIwMjUzOGM5ZGQmdHhUaW1lPTY5OEUxMTQ1",
                "label": "CH-NA"
            },
            {
                "url": "https://multi.govoet.cc/?hls=aHR0cHM6Ly9saXZlMS56dXFpdXp1cWl1enVxaXV6dXFpdS5jb20vc3BvcnQvMjAyXzQ3ODQxMTZfMS5tM3U4",
                "label": "CH-NA"
            }
        ]
    },
    {
        "id": "PAOK-Panathinaikos",
        "sport": "Football",
        "league": "Greek Cup",
        "team1": {
            "name": "PAOK",
            "logo": "https://ikotv.com/storage/logos/KQW4V6FG-pvWT1yik (2).png"
        },
        "team2": {
            "name": "Panathinaikos",
            "logo": "https://ikotv.com/storage/logos/Me3pW6Ea-GM4Cu0wi (2).png"
        },
        "kickoff_date": "2026-02-12",
        "kickoff_time": "01:30",
        "match_date": "2026-02-12",
        "match_time": "01:30",
        "duration": "3.5",
        "servers": [
            {
                "url": "https://multi.govoet.cc/?hls=aHR0cHM6Ly90ZXN0LmJ0eXNvMTYuY29tL2xpdmUvc2QtNk12WXFySG5uZ0NQR2NrUlJoLm0zdTg/dHhTZWNyZXQ9Mjk1NDBhN2E5OTVmMzJlYjBkNjIwZmM5OGViODcxMDEmdHhUaW1lPTY5OEUxQzRB",
                "label": "CH-NA"
            },
            {
                "url": "https://multi.govoet.cc/?hls=aHR0cHM6Ly9saXZlMS56dXFpdXp1cWl1enVxaXV6dXFpdS5jb20vc3BvcnQvMjAyXzQ4ODI4MzlfMTAubTN1OA==",
                "label": "CH-NA"
            }
        ]
    }
]